[
    {
        "key": "dbln",
        "value": "%7B%2261583347145821%22%3A%22UV6AsXTQ%22%7D",
        "domain": "facebook.com",
        "path": "/login/device-based/",
        "hostOnly": false,
        "creation": "2025-11-19T16:20:13.155Z",
        "lastAccessed": "2025-11-19T16:20:13.155Z"
    },
    {
        "key": "datr",
        "value": "po8caaS_8mPXecxgM4tOGf67",
        "domain": "facebook.com",
        "path": "/",
        "hostOnly": false,
        "creation": "2025-11-19T16:20:13.155Z",
        "lastAccessed": "2025-11-19T16:20:13.155Z"
    },
    {
        "key": "sb",
        "value": "po8caazvvDyBC5qvzRFfJUn-",
        "domain": "facebook.com",
        "path": "/",
        "hostOnly": false,
        "creation": "2025-11-19T16:20:13.155Z",
        "lastAccessed": "2025-11-19T16:20:13.155Z"
    },
    {
        "key": "c_user",
        "value": "61583347145821",
        "domain": "facebook.com",
        "path": "/",
        "hostOnly": false,
        "creation": "2025-11-19T16:20:13.155Z",
        "lastAccessed": "2025-11-19T16:20:13.155Z"
    },
    {
        "key": "xs",
        "value": "29%3AVujVsjGAWT86sA%3A2%3A1763479488%3A-1%3A-1",
        "domain": "facebook.com",
        "path": "/",
        "hostOnly": false,
        "creation": "2025-11-19T16:20:13.155Z",
        "lastAccessed": "2025-11-19T16:20:13.155Z"
    },
    {
        "key": "locale",
        "value": "en_US",
        "domain": "facebook.com",
        "path": "/",
        "hostOnly": false,
        "creation": "2025-11-19T16:20:13.155Z",
        "lastAccessed": "2025-11-19T16:20:13.155Z"
    },
    {
        "key": "pas",
        "value": "61583347145821%3AH7Yieb2jjf",
        "domain": "facebook.com",
        "path": "/",
        "hostOnly": false,
        "creation": "2025-11-19T16:20:13.155Z",
        "lastAccessed": "2025-11-19T16:20:13.155Z"
    },
    {
        "key": "vpd",
        "value": "v1%3B729x384x1.875",
        "domain": "facebook.com",
        "path": "/",
        "hostOnly": false,
        "creation": "2025-11-19T16:20:13.155Z",
        "lastAccessed": "2025-11-19T16:20:13.155Z"
    },
    {
        "key": "ps_l",
        "value": "1",
        "domain": "facebook.com",
        "path": "/",
        "hostOnly": false,
        "creation": "2025-11-19T16:20:13.155Z",
        "lastAccessed": "2025-11-19T16:20:13.155Z"
    },
    {
        "key": "ps_n",
        "value": "1",
        "domain": "facebook.com",
        "path": "/",
        "hostOnly": false,
        "creation": "2025-11-19T16:20:13.155Z",
        "lastAccessed": "2025-11-19T16:20:13.156Z"
    },
    {
        "key": "fr",
        "value": "0lEmOqH8SYxHosVSY.AWeLpdnIM2m7LPgh7lvmN-HI_7xsnyNf1GF5rbxjm2N8M3kLM4s.BpHI-m..AAA.0.0.BpHe41.AWeCuuVJUhZtEUbpyGViRdwMrhM",
        "domain": "facebook.com",
        "path": "/",
        "hostOnly": false,
        "creation": "2025-11-19T16:20:13.156Z",
        "lastAccessed": "2025-11-19T16:20:13.156Z"
    },
    {
        "key": "fbl_st",
        "value": "100630004%3BT%3A29392820",
        "domain": "facebook.com",
        "path": "/",
        "hostOnly": false,
        "creation": "2025-11-19T16:20:13.156Z",
        "lastAccessed": "2025-11-19T16:20:13.156Z"
    },
    {
        "key": "wl_cbv",
        "value": "v2%3Bclient_version%3A2989%3Btimestamp%3A1763569206",
        "domain": "facebook.com",
        "path": "/",
        "hostOnly": false,
        "creation": "2025-11-19T16:20:13.156Z",
        "lastAccessed": "2025-11-19T16:20:13.156Z"
    }
]
